{
  "abuelos": "[translation needed]",
  "académica": "[translation needed]",
  "acordamos": "[translation needed]",
  "actual": "[translation needed]",
  "adicionales": "[translation needed]",
  "algodones": "[translation needed]",
  "algodón": "[translation needed]",
  "algún": "[translation needed]",
  "alimentos": "[translation needed]",
  "allá": "[translation needed]",
  "alma": "[translation needed]",
  "almohada": "[translation needed]",
  "anestesia": "[translation needed]",
  "animales": "[translation needed]",
  "antepasados": "[translation needed]",
  "aquí": "[translation needed]",
  "ardilla": "[translation needed]",
  "ardillas": "[translation needed]",
  "arrancando": "[translation needed]",
  "atrás": "[translation needed]",
  "avanzada": "[translation needed]",
  "ayuda": "[translation needed]",
  "años": "[translation needed]",
  "bendecir": "[translation needed]",
  "bienvenidos": "[translation needed]",
  "blandos": "[translation needed]",
  "blink": "[translation needed]",
  "bola": "[translation needed]",
  "bolas": "[translation needed]",
  "boom": "[translation needed]",
  "boost": "[translation needed]",
  "calmó": "[translation needed]",
  "cambios": "[translation needed]",
  "camino": "[translation needed]",
  "camisas": "[translation needed]",
  "carnes": "[translation needed]",
  "casas": "[translation needed]",
  "chpt": "[translation needed]",
  "chute": "[translation needed]",
  "ciega": "[translation needed]",
  "coge": "[translation needed]",
  "cogemos": "[translation needed]",
  "cogen": "[translation needed]",
  "coman": "[translation needed]",
  "comen": "[translation needed]",
  "comentarios": "[translation needed]",
  "comida": "[translation needed]",
  "complet": "[translation needed]",
  "completamente": "[translation needed]",
  "consisten": "[translation needed]",
  "contar": "[translation needed]",
  "contexto": "[translation needed]",
  "corriendo": "[translation needed]",
  "cotton": "[translation needed]",
  "creemos": "[translation needed]",
  "creo": "[translation needed]",
  "cualquier": "[translation needed]",
  "culpes": "[translation needed]",
  "cute": "[translation needed]",
  "dado": "[translation needed]",
  "darme": "[translation needed]",
  "debido": "[translation needed]",
  "decimos": "[translation needed]",
  "deja": "[translation needed]",
  "dejan": "[translation needed]",
  "dejar": "[translation needed]",
  "dejarlo": "[translation needed]",
  "demás": "[translation needed]",
  "dentista": "[translation needed]",
  "dice": "[translation needed]",
  "diente": "[translation needed]",
  "dientes": "[translation needed]",
  "dieta": "[translation needed]",
  "dietas": "[translation needed]",
  "difíciles": "[translation needed]",
  "digerir": "[translation needed]",
  "dije": "[translation needed]",
  "dijo": "[translation needed]",
  "dramatic": "[translation needed]",
  "duelen": "[translation needed]",
  "duros": "[translation needed]",
  "déjame": "[translation needed]",
  "económica": "[translation needed]",
  "económicamente": "[translation needed]",
  "elegido": "[translation needed]",
  "encontramos": "[translation needed]",
  "encuentras": "[translation needed]",
  "ente": "[translation needed]",
  "entiendo": "[translation needed]",
  "episodio": "[translation needed]",
  "eres": "[translation needed]",
  "esfuerzo": "[translation needed]",
  "especial": "[translation needed]",
  "esquina": "[translation needed]",
  "estaba": "[translation needed]",
  "estaban": "[translation needed]",
  "estados": "[translation needed]",
  "estadounidenses": "[translation needed]",
  "estoy": "[translation needed]",
  "está": "[translation needed]",
  "están": "[translation needed]",
  "evolución": "[translation needed]",
  "evolutivo": "[translation needed]",
  "excusa": "[translation needed]",
  "experiencia": "[translation needed]",
  "explicar": "[translation needed]",
  "explotar": "[translation needed]",
  "extras": "[translation needed]",
  "facial": "[translation needed]",
  "fairy": "[translation needed]",
  "fibrosos": "[translation needed]",
  "fritas": "[translation needed]",
  "fuente": "[translation needed]",
  "fuera": "[translation needed]",
  "haber": "[translation needed]",
  "hablamos": "[translation needed]",
  "hace": "[translation needed]",
  "hacen": "[translation needed]",
  "hadas": "[translation needed]",
  "hechas": "[translation needed]",
  "helado": "[translation needed]",
  "heredado": "[translation needed]",
  "hizo": "[translation needed]",
  "hueso": "[translation needed]",
  "humanos": "[translation needed]",
  "hámster": "[translation needed]",
  "inglés": "[translation needed]",
  "intento": "[translation needed]",
  "interesa": "[translation needed]",
  "interesante": "[translation needed]",
  "inútil": "[translation needed]",
  "juicio": "[translation needed]",
  "later": "[translation needed]",
  "like": "[translation needed]",
  "little": "[translation needed]",
  "llaman": "[translation needed]",
  "llamen": "[translation needed]",
  "llegué": "[translation needed]",
  "luigi": "[translation needed]",
  "make": "[translation needed]",
  "mams": "[translation needed]",
  "mamuts": "[translation needed]",
  "mandíbula": "[translation needed]",
  "mandíbulas": "[translation needed]",
  "manera": "[translation needed]",
  "manolo": "[translation needed]",
  "masticando": "[translation needed]",
  "masticar": "[translation needed]",
  "matado": "[translation needed]",
  "matando": "[translation needed]",
  "material": "[translation needed]",
  "mayoría": "[translation needed]",
  "menciono": "[translation needed]",
  "merecemos": "[translation needed]",
  "mete": "[translation needed]",
  "moler": "[translation needed]",
  "moneda": "[translation needed]",
  "morder": "[translation needed]",
  "morderte": "[translation needed]",
  "mordiscos": "[translation needed]",
  "more": "[translation needed]",
  "morfología": "[translation needed]",
  "mouse": "[translation needed]",
  "muchísimo": "[translation needed]",
  "muela": "[translation needed]",
  "muelas": "[translation needed]",
  "máximo": "[translation needed]",
  "necesarias": "[translation needed]",
  "necesidad": "[translation needed]",
  "necesita": "[translation needed]",
  "necesitaban": "[translation needed]",
  "niño": "[translation needed]",
  "niños": "[translation needed]",
  "normalmente": "[translation needed]",
  "nueces": "[translation needed]",
  "nuevos": "[translation needed]",
  "observé": "[translation needed]",
  "obviously": "[translation needed]",
  "operación": "[translation needed]",
  "outside": "[translation needed]",
  "padecer": "[translation needed]",
  "palabra": "[translation needed]",
  "paquete": "[translation needed]",
  "parecía": "[translation needed]",
  "pasa": "[translation needed]",
  "paseo": "[translation needed]",
  "patatas": "[translation needed]",
  "pegando": "[translation needed]",
  "pensé": "[translation needed]",
  "perfecto": "[translation needed]",
  "perlas": "[translation needed]",
  "personas": "[translation needed]",
  "pico": "[translation needed]",
  "plástico": "[translation needed]",
  "podía": "[translation needed]",
  "ponerme": "[translation needed]",
  "pregunta": "[translation needed]",
  "primer": "[translation needed]",
  "problemas": "[translation needed]",
  "procesados": "[translation needed]",
  "procesar": "[translation needed]",
  "próximo": "[translation needed]",
  "pudiendo": "[translation needed]",
  "puedes": "[translation needed]",
  "puedo": "[translation needed]",
  "punto": "[translation needed]",
  "puse": "[translation needed]",
  "puso": "[translation needed]",
  "pérez": "[translation needed]",
  "rareza": "[translation needed]",
  "ratoncito": "[translation needed]",
  "ratones": "[translation needed]",
  "rats": "[translation needed]",
  "ratón": "[translation needed]",
  "raíces": "[translation needed]",
  "raíz": "[translation needed]",
  "reducido": "[translation needed]",
  "regalito": "[translation needed]",
  "respetada": "[translation needed]",
  "respirar": "[translation needed]",
  "respondió": "[translation needed]",
  "resto": "[translation needed]",
  "restos": "[translation needed]",
  "romper": "[translation needed]",
  "rous": "[translation needed]",
  "rápida": "[translation needed]",
  "sabes": "[translation needed]",
  "sabiduría": "[translation needed]",
  "saca": "[translation needed]",
  "sacado": "[translation needed]",
  "sacaron": "[translation needed]",
  "sacándome": "[translation needed]",
  "sacó": "[translation needed]",
  "salen": "[translation needed]",
  "salí": "[translation needed]",
  "sanar": "[translation needed]",
  "sangre": "[translation needed]",
  "sense": "[translation needed]",
  "sentido": "[translation needed]",
  "sentí": "[translation needed]",
  "serious": "[translation needed]",
  "situación": "[translation needed]",
  "smith": "[translation needed]",
  "spanish": "[translation needed]",
  "sucia": "[translation needed]",
  "sufrir": "[translation needed]",
  "superior": "[translation needed]",
  "supongo": "[translation needed]",
  "surprise": "[translation needed]",
  "talento": "[translation needed]",
  "tenéis": "[translation needed]",
  "tenían": "[translation needed]",
  "teoría": "[translation needed]",
  "texto": "[translation needed]",
  "tocado": "[translation needed]",
  "tonta": "[translation needed]",
  "tooth": "[translation needed]",
  "tragic": "[translation needed]",
  "tranquila": "[translation needed]",
  "triturar": "[translation needed]",
  "tucutu": "[translation needed]",
  "tumbaden": "[translation needed]",
  "tuut": "[translation needed]",
  "unidos": "[translation needed]",
  "useful": "[translation needed]",
  "uñas": "[translation needed]",
  "vemos": "[translation needed]",
  "venga": "[translation needed]",
  "vestigio": "[translation needed]",
  "viene": "[translation needed]",
  "vivos": "[translation needed]",
  "walk": "[translation needed]",
  "will": "[translation needed]",
  "wink": "[translation needed]",
  "wisdom": "[translation needed]",
  "época": "[translation needed]",
  "único": "[translation needed]",
  "útiles": "[translation needed]"
}